odoo/addons/website_sale_stock_list_preview/README.rst
odoo/addons/website_sale_stock_list_preview/__init__.py
odoo/addons/website_sale_stock_list_preview/__manifest__.py
odoo/addons/website_sale_stock_list_preview/controllers/__init__.py
odoo/addons/website_sale_stock_list_preview/controllers/main.py
odoo/addons/website_sale_stock_list_preview/i18n/es.po
odoo/addons/website_sale_stock_list_preview/i18n/website_sale_stock_list_preview.pot
odoo/addons/website_sale_stock_list_preview/readme/CONTRIBUTORS.rst
odoo/addons/website_sale_stock_list_preview/readme/DESCRIPTION.rst
odoo/addons/website_sale_stock_list_preview/readme/USAGE.rst
odoo/addons/website_sale_stock_list_preview/static/description/icon.png
odoo/addons/website_sale_stock_list_preview/static/description/index.html
odoo/addons/website_sale_stock_list_preview/static/src/js/tour.js
odoo/addons/website_sale_stock_list_preview/static/src/js/website_sale_stock_list_preview.js
odoo/addons/website_sale_stock_list_preview/tests/__init__.py
odoo/addons/website_sale_stock_list_preview/tests/test_ui.py
odoo/addons/website_sale_stock_list_preview/views/assets.xml
odoo/addons/website_sale_stock_list_preview/views/templates.xml
odoo13_addon_website_sale_stock_list_preview-13.0.1.1.2.dist-info/METADATA
odoo13_addon_website_sale_stock_list_preview-13.0.1.1.2.dist-info/WHEEL
odoo13_addon_website_sale_stock_list_preview-13.0.1.1.2.dist-info/top_level.txt
odoo13_addon_website_sale_stock_list_preview-13.0.1.1.2.dist-info/RECORD
